seg2stream/__init__.py
seg2stream/seg2generator.py
seg2stream/seg2stream.py
seg2stream/segmenters.py
seg2stream-1.0.2.dist-info/METADATA
seg2stream-1.0.2.dist-info/WHEEL
seg2stream-1.0.2.dist-info/top_level.txt
seg2stream-1.0.2.dist-info/RECORD
