Metadata-Version: 2.4
Name: seg2stream
Version: 1.0.2
Summary: Real-time pipeline for segmenting text into a sentence stream.
Home-page: https://github.com/shenduldh/seg2stream
Author: Daking Liou
Author-email: lioudaking@foxmail.com
Keywords: sentence segmentation,tts
Classifier: Programming Language :: Python :: 3
Classifier: License :: OSI Approved :: MIT License
Classifier: Operating System :: OS Independent
Requires-Python: >=3.10
Provides-Extra: optional
Requires-Dist: stanza==1.10.1; extra == "optional"
Dynamic: author
Dynamic: author-email
Dynamic: classifier
Dynamic: description
Dynamic: description-content-type
Dynamic: home-page
Dynamic: keywords
Dynamic: provides-extra
Dynamic: requires-python
Dynamic: summary
